textdescriptives/__init__.py
textdescriptives/about.py
textdescriptives/extractors.py
textdescriptives/load_components.py
textdescriptives/utils.py
textdescriptives/components/__init__.py
textdescriptives/components/coherence.py
textdescriptives/components/dependency_distance.py
textdescriptives/components/descriptive_stats.py
textdescriptives/components/information_theory.py
textdescriptives/components/pos_proportions.py
textdescriptives/components/quality.py
textdescriptives/components/quality_data_classes.py
textdescriptives/components/readability.py
textdescriptives/components/utils.py
textdescriptives/data/spam.csv
textdescriptives/integrations/__init__.py
textdescriptives/integrations/sklearn_featurizer.py
textdescriptives-2.8.4.dist-info/LICENSE
textdescriptives-2.8.4.dist-info/METADATA
textdescriptives-2.8.4.dist-info/WHEEL
textdescriptives-2.8.4.dist-info/top_level.txt
textdescriptives-2.8.4.dist-info/RECORD
