Metadata-Version: 2.1
Name: textdescriptives
Version: 2.8.4
Summary: A library for calculating a variety of features from text using spaCy
Author: Kenneth Enevoldsen
Author-email: Lasse Hansen <lasseh0310@gmail.com>
License:                                  Apache License
Project-URL: homepage, https://hlasse.github.io/TextDescriptives/
Project-URL: repository, https://github.com/HLasse/textdescriptives
Project-URL: documentation, https://hlasse.github.io/TextDescriptives/
Keywords: NLP,spaCy,text analysis,natural language processing,text features,text statistics,text descriptives,text analytics,text mining
Classifier: Development Status :: 5 - Production/Stable
Classifier: Environment :: Console
Classifier: Intended Audience :: Developers
Classifier: Intended Audience :: Science/Research
Classifier: Topic :: Scientific/Engineering
Classifier: Topic :: Scientific/Engineering :: Artificial Intelligence
Classifier: Operating System :: POSIX :: Linux
Classifier: Operating System :: MacOS :: MacOS X
Classifier: Operating System :: Microsoft :: Windows
Classifier: Programming Language :: Python :: 3
Classifier: Programming Language :: Python :: 3.9
Classifier: Programming Language :: Python :: 3.10
Classifier: Programming Language :: Python :: 3.11
Classifier: Programming Language :: Python :: 3.12
Classifier: Programming Language :: Python :: 3.13
Requires-Python: >=3.9
License-File: LICENSE
Requires-Dist: spacy[lookups]>=3.6.0
Requires-Dist: numpy<2.0.0,>=1.20.0
Requires-Dist: pandas>=1.0.0
Requires-Dist: pyphen>=0.11.0
Requires-Dist: ftfy>=6.0.3
Requires-Dist: pydantic>=2.0
Provides-Extra: style
Requires-Dist: ruff==0.8.3; extra == "style"
Provides-Extra: tests
Requires-Dist: pytest>=7.1.3; extra == "tests"
Requires-Dist: pytest-cov>=3.0.0; extra == "tests"
Requires-Dist: pytest-xdist; extra == "tests"
Provides-Extra: docs
Requires-Dist: pydantic==2.1; extra == "docs"
Requires-Dist: sphinx>=5.3.0; extra == "docs"
Requires-Dist: furo==2022.12.7; extra == "docs"
Requires-Dist: sphinx-copybutton>=0.5.1; extra == "docs"
Requires-Dist: sphinxext-opengraph>=0.7.3; extra == "docs"
Requires-Dist: myst-nb>=0.6.0; extra == "docs"
Requires-Dist: sphinx_design>=0.3.0; extra == "docs"
Requires-Dist: autodoc_pydantic==2.1.0; extra == "docs"
Provides-Extra: tutorials
Requires-Dist: jupyter; extra == "tutorials"
Requires-Dist: seaborn==0.13.2; extra == "tutorials"
Requires-Dist: matplotlib; extra == "tutorials"
Requires-Dist: datasets>=2.8.0; extra == "tutorials"
Requires-Dist: scikit-learn>=1.1.1; extra == "tutorials"
Requires-Dist: scipy>=1.13.1; extra == "tutorials"
Requires-Dist: ipython<=8.21.0; extra == "tutorials"
Provides-Extra: sklearn
Requires-Dist: scikit-learn>=1.1.1; extra == "sklearn"
